{
  "tutors": [
    {
      "image": "https://api.adorable.io/avatars/260x260/1",
      "id": 1,
      "name": "Mcconnell Bowers",
      "students": [
        {
          "image": "https://api.adorable.io/avatars/30x30/12"
        },
        {
          "image": "https://api.adorable.io/avatars/30x30/11"
        },
        {
          "image": "https://api.adorable.io/avatars/30x30/27"
        },
        {
          "image": "https://api.adorable.io/avatars/30x30/8"
        }
      ],
      "city": "Manchester"
    },
    {
      "image": "https://api.adorable.io/avatars/260x260/2",
      "id": 2,
      "name": "Lidia Travis",
      "students": [
        {
          "image": "https://api.adorable.io/avatars/30x30/3"
        }
      ],
      "city": "London"
    },
    {
      "image": "https://api.adorable.io/avatars/260x260/3",
      "id": 3,
      "name": "Tamika Newton",
      "students": [
        {
          "image": "https://api.adorable.io/avatars/30x30/21"
        }
      ],
      "city": "London"
    },
    {
      "image": "https://api.adorable.io/avatars/260x260/4",
      "id": 4,
      "name": "Selena Guerrero",
      "students": [
        {
          "image": "https://api.adorable.io/avatars/30x30/24"
        },
        {
          "image": "https://api.adorable.io/avatars/30x30/1"
        },
        {
          "image": "https://api.adorable.io/avatars/30x30/20"
        },
        {
          "image": "https://api.adorable.io/avatars/30x30/3"
        }
      ],
      "city": "Manchester"
    },
    {
      "image": "https://api.adorable.io/avatars/260x260/5",
      "id": 5,
      "name": "Woodward Brady",
      "students": [
        {
          "image": "https://api.adorable.io/avatars/30x30/15"
        },
        {
          "image": "https://api.adorable.io/avatars/30x30/6"
        },
        {
          "image": "https://api.adorable.io/avatars/30x30/25"
        }
      ],
      "city": "London"
    },
    {
      "image": "https://api.adorable.io/avatars/260x260/6",
      "id": 6,
      "name": "Holman West",
      "students": [
        {
          "image": "https://api.adorable.io/avatars/30x30/4"
        },
        {
          "image": "https://api.adorable.io/avatars/30x30/30"
        },
        {
          "image": "https://api.adorable.io/avatars/30x30/29"
        },
        {
          "image": "https://api.adorable.io/avatars/30x30/11"
        }
      ],
      "city": "Manchester"
    },
    {
      "image": "https://api.adorable.io/avatars/260x260/7",
      "id": 7,
      "name": "Isabella Tillman",
      "students": [
        {
          "image": "https://api.adorable.io/avatars/30x30/7"
        },
        {
          "image": "https://api.adorable.io/avatars/30x30/30"
        }
      ],
      "city": "London"
    },
    {
      "image": "https://api.adorable.io/avatars/260x260/8",
      "id": 8,
      "name": "Gould Blevins",
      "students": [
        {
          "image": "https://api.adorable.io/avatars/30x30/27"
        },
        {
          "image": "https://api.adorable.io/avatars/30x30/25"
        },
        {
          "image": "https://api.adorable.io/avatars/30x30/15"
        },
        {
          "image": "https://api.adorable.io/avatars/30x30/6"
        },
        {
          "image": "https://api.adorable.io/avatars/30x30/21"
        }
      ],
      "city": "Manchester"
    },
    {
      "image": "https://api.adorable.io/avatars/260x260/9",
      "id": 9,
      "name": "Francesca Clayton",
      "students": [
        {
          "image": "https://api.adorable.io/avatars/30x30/30"
        }
      ],
      "city": "Manchester"
    },
    {
      "image": "https://api.adorable.io/avatars/260x260/10",
      "id": 10,
      "name": "Townsend Gilmore",
      "students": [
        {
          "image": "https://api.adorable.io/avatars/30x30/28"
        }
      ],
      "city": "Manchester"
    },
    {
      "image": "https://api.adorable.io/avatars/260x260/11",
      "id": 11,
      "name": "Pollard Brooks",
      "students": [
        {
          "image": "https://api.adorable.io/avatars/30x30/20"
        },
        {
          "image": "https://api.adorable.io/avatars/30x30/5"
        },
        {
          "image": "https://api.adorable.io/avatars/30x30/7"
        },
        {
          "image": "https://api.adorable.io/avatars/30x30/14"
        },
        {
          "image": "https://api.adorable.io/avatars/30x30/12"
        }
      ],
      "city": "Liverpool"
    },
    {
      "image": "https://api.adorable.io/avatars/260x260/12",
      "id": 12,
      "name": "Boone Perkins",
      "students": [
        {
          "image": "https://api.adorable.io/avatars/30x30/16"
        },
        {
          "image": "https://api.adorable.io/avatars/30x30/4"
        },
        {
          "image": "https://api.adorable.io/avatars/30x30/19"
        }
      ],
      "city": "London"
    },
    {
      "image": "https://api.adorable.io/avatars/260x260/13",
      "id": 13,
      "name": "Vincent Keith",
      "students": [
        {
          "image": "https://api.adorable.io/avatars/30x30/21"
        },
        {
          "image": "https://api.adorable.io/avatars/30x30/23"
        },
        {
          "image": "https://api.adorable.io/avatars/30x30/24"
        }
      ],
      "city": "London"
    },
    {
      "image": "https://api.adorable.io/avatars/260x260/14",
      "id": 14,
      "name": "Brittany Luna",
      "students": [
        {
          "image": "https://api.adorable.io/avatars/30x30/24"
        },
        {
          "image": "https://api.adorable.io/avatars/30x30/11"
        }
      ],
      "city": "London"
    },
    {
      "image": "https://api.adorable.io/avatars/260x260/15",
      "id": 15,
      "name": "House Mcguire",
      "students": [
        {
          "image": "https://api.adorable.io/avatars/30x30/14"
        },
        {
          "image": "https://api.adorable.io/avatars/30x30/18"
        },
        {
          "image": "https://api.adorable.io/avatars/30x30/10"
        }
      ],
      "city": "Liverpool"
    },
    {
      "image": "https://api.adorable.io/avatars/260x260/16",
      "id": 16,
      "name": "Goff Kirby",
      "students": [
        {
          "image": "https://api.adorable.io/avatars/30x30/12"
        },
        {
          "image": "https://api.adorable.io/avatars/30x30/5"
        },
        {
          "image": "https://api.adorable.io/avatars/30x30/16"
        },
        {
          "image": "https://api.adorable.io/avatars/30x30/13"
        }
      ],
      "city": "Liverpool"
    },
    {
      "image": "https://api.adorable.io/avatars/260x260/17",
      "id": 17,
      "name": "Emerson Alvarado",
      "students": [
        {
          "image": "https://api.adorable.io/avatars/30x30/23"
        },
        {
          "image": "https://api.adorable.io/avatars/30x30/11"
        },
        {
          "image": "https://api.adorable.io/avatars/30x30/7"
        },
        {
          "image": "https://api.adorable.io/avatars/30x30/10"
        }
      ],
      "city": "London"
    },
    {
      "image": "https://api.adorable.io/avatars/260x260/18",
      "id": 18,
      "name": "Stone Hart",
      "students": [
        {
          "image": "https://api.adorable.io/avatars/30x30/1"
        },
        {
          "image": "https://api.adorable.io/avatars/30x30/22"
        },
        {
          "image": "https://api.adorable.io/avatars/30x30/6"
        },
        {
          "image": "https://api.adorable.io/avatars/30x30/21"
        },
        {
          "image": "https://api.adorable.io/avatars/30x30/27"
        }
      ],
      "city": "Liverpool"
    },
    {
      "image": "https://api.adorable.io/avatars/260x260/19",
      "id": 19,
      "name": "Randall Stewart",
      "students": [
        {
          "image": "https://api.adorable.io/avatars/30x30/1"
        }
      ],
      "city": "Manchester"
    },
    {
      "image": "https://api.adorable.io/avatars/260x260/20",
      "id": 20,
      "name": "Pruitt Owen",
      "students": [
        {
          "image": "https://api.adorable.io/avatars/30x30/3"
        },
        {
          "image": "https://api.adorable.io/avatars/30x30/1"
        },
        {
          "image": "https://api.adorable.io/avatars/30x30/11"
        },
        {
          "image": "https://api.adorable.io/avatars/30x30/28"
        },
        {
          "image": "https://api.adorable.io/avatars/30x30/2"
        },
        {
          "image": "https://api.adorable.io/avatars/30x30/4"
        }
      ],
      "city": "London"
    },
    {
      "image": "https://api.adorable.io/avatars/260x260/21",
      "id": 21,
      "name": "Kristi Shelton",
      "students": [
        {
          "image": "https://api.adorable.io/avatars/30x30/4"
        },
        {
          "image": "https://api.adorable.io/avatars/30x30/26"
        },
        {
          "image": "https://api.adorable.io/avatars/30x30/1"
        },
        {
          "image": "https://api.adorable.io/avatars/30x30/3"
        }
      ],
      "city": "London"
    }
  ],
  "cities": [
    {
      "id": 1,
      "name": "London"
    },
    {
      "id": 2,
      "name": "Manchester"
    },
    {
      "id": 3,
      "name": "Liverpool"
    }
  ],
  "profile": {
    "name": "typicode"
  }
}
